{
  "description": "Run the full experiment suite: default multi-seed robustness plus standalone strong-attack recovery diagnostics.",
  "default_robustness": {
    "enabled": true,
    "seeds": "0-4",
    "config": "configs/ppo_robustness_experiment.json",
    "output_root": "runs/robustness"
  },
  "strong_attack_recovery": {
    "enabled": true,
    "config": "configs/strong_attack_recovery_experiment.json",
    "checkpoint": "runs/robustness/seed0/nominal_ppo/checkpoint.pt",
    "output_root": "runs/strong_attack_recovery"
  },
  "logs": {
    "output_dir": "runs/experiment_suite_logs"
  }
}
